pdslogger/__init__.py
pdslogger/_finder_colors.py
pdslogger/_version.py
rms_pdslogger-3.2.1.dist-info/licenses/LICENSE
rms_pdslogger-3.2.1.dist-info/METADATA
rms_pdslogger-3.2.1.dist-info/WHEEL
rms_pdslogger-3.2.1.dist-info/top_level.txt
rms_pdslogger-3.2.1.dist-info/RECORD
