Metadata-Version: 2.4
Name: rms-pdslogger
Version: 3.2.1
Summary: Extension to the Python logging module
Maintainer-email: "Robert S. French" <rfrench@seti.org>
License: Apache-2.0
Project-URL: Homepage, https://github.com/SETI/rms-pdslogger
Project-URL: Repository, https://github.com/SETI/rms-pdslogger
Project-URL: Source, https://github.com/SETI/rms-pdslogger
Project-URL: Issues, https://github.com/SETI/rms-pdslogger/issues
Keywords: pdslogger
Classifier: Development Status :: 5 - Production/Stable
Classifier: Natural Language :: English
Classifier: Topic :: Scientific/Engineering
Classifier: Topic :: Software Development :: Libraries :: Python Modules
Classifier: Topic :: Utilities
Classifier: License :: OSI Approved :: Apache Software License
Classifier: Programming Language :: Python :: 3.10
Classifier: Programming Language :: Python :: 3.11
Classifier: Programming Language :: Python :: 3.12
Classifier: Programming Language :: Python :: 3.13
Classifier: Operating System :: MacOS :: MacOS X
Classifier: Operating System :: POSIX :: Linux
Classifier: Operating System :: Microsoft :: Windows
Requires-Python: >=3.10
License-File: LICENSE
Requires-Dist: rms-filecache
Requires-Dist: xattr; platform_system != "Windows"
Dynamic: license-file
